Metadata-Version: 2.4
Name: lds-merkle-proof-2019-bloxberg2
Version: 1.0.4
Summary: MerkleProof2019 module for python
Home-page: https://gitlab.mpcdf.mpg.de/cert-issuer/lds-merkle-proof-2019-py
Author: bloxberg2
Author-email: info@bloxberg.org
License: MIT
License-File: LICENSE
Requires-Dist: py-multibase>=1.0.1
Requires-Dist: cbor2>=4.1.2
Dynamic: author
Dynamic: author-email
Dynamic: description
Dynamic: description-content-type
Dynamic: home-page
Dynamic: license
Dynamic: license-file
Dynamic: requires-dist
Dynamic: summary
